okdata_cli-6.0.0-py3.13-nspkg.pth
okdata/cli/__init__.py
okdata/cli/__main__.py
okdata/cli/command.py
okdata/cli/io.py
okdata/cli/output.py
okdata/cli/commands/__init__.py
okdata/cli/commands/permissions.py
okdata/cli/commands/status.py
okdata/cli/commands/validators.py
okdata/cli/commands/wizard.py
okdata/cli/commands/datasets/__init__.py
okdata/cli/commands/datasets/datasets.py
okdata/cli/commands/datasets/questions.py
okdata/cli/commands/datasets/wizards.py
okdata/cli/commands/pubs/__init__.py
okdata/cli/commands/pubs/clients.py
okdata/cli/commands/pubs/pubs.py
okdata/cli/commands/pubs/questions.py
okdata/cli/commands/pubs/wizards.py
okdata/cli/commands/teams/questions.py
okdata/cli/commands/teams/teams.py
okdata/cli/commands/teams/util.py
okdata/cli/commands/teams/wizards.py
okdata/cli/data/output-format/datasets_config.json
okdata/cli/data/output-format/datasets_config_verbose.json
okdata/cli/data/output-format/datasets_copy_file_config.json
okdata/cli/data/output-format/datasets_copy_file_config_2.json
okdata/cli/data/output-format/datasets_dataset_config.json
okdata/cli/data/output-format/datasets_dataset_version_config.json
okdata/cli/data/output-format/datasets_dataset_version_edition_config.json
okdata/cli/data/output-format/datasets_dataset_version_edition_distributions_config.json
okdata/cli/data/output-format/datasets_dataset_versions_config.json
okdata/cli/data/output-format/my_permissions_config.json
okdata/cli/data/output-format/permissions_config.json
okdata/cli/data/output-format/pubs_audit_log_config.json
okdata/cli/data/output-format/pubs_clients_config.json
okdata/cli/data/output-format/pubs_multiple_client_keys_config.json
okdata/cli/data/output-format/pubs_single_client_keys_config.json
okdata/cli/data/output-format/status_config.json
okdata/cli/data/output-format/status_history_config.json
okdata/cli/data/output-format/team_members_config.json
okdata/cli/data/output-format/teams_config.json
okdata_cli-6.0.0.dist-info/licenses/LICENSE
okdata_cli-6.0.0.dist-info/METADATA
okdata_cli-6.0.0.dist-info/WHEEL
okdata_cli-6.0.0.dist-info/entry_points.txt
okdata_cli-6.0.0.dist-info/namespace_packages.txt
okdata_cli-6.0.0.dist-info/top_level.txt
okdata_cli-6.0.0.dist-info/RECORD
