Metadata-Version: 2.4
Name: okdata-cli
Version: 6.0.0
Summary: CLI for services provided by Oslo Origo
Home-page: https://github.com/oslokommune/okdata-cli/
Author: Oslo Origo
Author-email: dataspeilet@oslo.kommune.no
License: MIT
Classifier: Development Status :: 5 - Production/Stable
Classifier: Programming Language :: Python :: 3.10
Classifier: Programming Language :: Python :: 3.11
Classifier: Programming Language :: Python :: 3.12
Classifier: Programming Language :: Python :: 3.13
Classifier: Programming Language :: Python :: 3.14
Classifier: License :: OSI Approved :: MIT License
Classifier: Operating System :: OS Independent
Requires-Python: >=3.10
License-File: LICENSE
Requires-Dist: docopt
Requires-Dist: okdata-sdk<5,>=4
Requires-Dist: PrettyTable
Requires-Dist: questionary<2.0.0,>=1.10.0
Requires-Dist: prompt-toolkit<3.0.52
Requires-Dist: requests
Dynamic: author
Dynamic: author-email
Dynamic: classifier
Dynamic: description
Dynamic: description-content-type
Dynamic: home-page
Dynamic: license
Dynamic: license-file
Dynamic: requires-dist
Dynamic: requires-python
Dynamic: summary
